posh/__init__.py
posh/posh.py
py_posh-1.2.2.dist-info/LICENSE
py_posh-1.2.2.dist-info/METADATA
py_posh-1.2.2.dist-info/WHEEL
py_posh-1.2.2.dist-info/top_level.txt
py_posh-1.2.2.dist-info/RECORD
