Metadata-Version: 2.1
Name: py-posh
Version: 1.2.2
Summary: A python shell
Home-page: https://github.com/gJager/posh
Author: Graeme Jager
Author-email: graemejager@gmail.com
License: MIT License
Platform: UNKNOWN
License-File: LICENSE
